image_enhancer/__init__.py
image_enhancer/enhancer.py
tests/__init__.py
tests/test_enhancer.py
image_enhancer-0.1.3.dist-info/METADATA
image_enhancer-0.1.3.dist-info/WHEEL
image_enhancer-0.1.3.dist-info/top_level.txt
image_enhancer-0.1.3.dist-info/RECORD
