Metadata-Version: 2.1
Name: image-enhancer
Version: 0.1.3
Summary: A package for enhancing images with various filters and adjustments
Home-page: https://github.com/yourusername/image-enhancer
Author: Your Name
Author-email: your.email@example.com
Classifier: Programming Language :: Python :: 3
Classifier: License :: OSI Approved :: MIT License
Classifier: Operating System :: OS Independent
Requires-Python: >=3.6
Requires-Dist: opencv-python
Requires-Dist: numpy
Requires-Dist: Pillow
Requires-Dist: requests
